odoo8_addon_magentoerpconnect_pricing-8.0.2.0.0.99.dev22-py3.8-nspkg.pth
odoo_addons/magentoerpconnect_pricing/README.rst
odoo_addons/magentoerpconnect_pricing/__init__.py
odoo_addons/magentoerpconnect_pricing/__openerp__.py
odoo_addons/magentoerpconnect_pricing/magento_model.py
odoo_addons/magentoerpconnect_pricing/magento_model_view.xml
odoo_addons/magentoerpconnect_pricing/product.py
odoo_addons/magentoerpconnect_pricing/sale.py
odoo_addons/magentoerpconnect_pricing/i18n/ca.po
odoo_addons/magentoerpconnect_pricing/i18n/de.po
odoo_addons/magentoerpconnect_pricing/i18n/es.po
odoo_addons/magentoerpconnect_pricing/i18n/fr.po
odoo_addons/magentoerpconnect_pricing/i18n/it.po
odoo_addons/magentoerpconnect_pricing/i18n/magentoerpconnect_pricing.pot
odoo_addons/magentoerpconnect_pricing/i18n/nl.po
odoo_addons/magentoerpconnect_pricing/i18n/pt_BR.po
odoo_addons/magentoerpconnect_pricing/i18n/sl.po
odoo_addons/magentoerpconnect_pricing/i18n/tr.po
odoo_addons/magentoerpconnect_pricing/i18n/tr_TR.po
odoo_addons/magentoerpconnect_pricing/static/description/icon.png
odoo_addons/magentoerpconnect_pricing/tests/__init__.py
odoo_addons/magentoerpconnect_pricing/tests/test_export_price.py
odoo_addons/magentoerpconnect_pricing/tests/test_import_price.py
odoo8_addon_magentoerpconnect_pricing-8.0.2.0.0.99.dev22.dist-info/METADATA
odoo8_addon_magentoerpconnect_pricing-8.0.2.0.0.99.dev22.dist-info/WHEEL
odoo8_addon_magentoerpconnect_pricing-8.0.2.0.0.99.dev22.dist-info/namespace_packages.txt
odoo8_addon_magentoerpconnect_pricing-8.0.2.0.0.99.dev22.dist-info/top_level.txt
odoo8_addon_magentoerpconnect_pricing-8.0.2.0.0.99.dev22.dist-info/RECORD
